windeployqt/deploy.py
windeployqt/desktop.py
windeployqt/main.py
windeployqt-2025.2.5.0.dist-info/METADATA
windeployqt-2025.2.5.0.dist-info/WHEEL
windeployqt-2025.2.5.0.dist-info/entry_points.txt
windeployqt-2025.2.5.0.dist-info/licenses/LICENSE
windeployqt-2025.2.5.0.dist-info/RECORD
