Metadata-Version: 2.4
Name: windeployqt
Version: 2025.2.5.0
Summary: deploy Qt app using MSYS2
Project-URL: Repository, https://github.com/soda92/windeployqt
License-File: LICENSE
Requires-Python: >=3.10
Requires-Dist: pywin32>=308
